binderlite/__init__.py
binderlite/run.py
repo2jupyterlite/__init__.py
repo2jupyterlite/app.py
repo2jupyterlite-0.2.dist-info/LICENSE
repo2jupyterlite-0.2.dist-info/METADATA
repo2jupyterlite-0.2.dist-info/WHEEL
repo2jupyterlite-0.2.dist-info/entry_points.txt
repo2jupyterlite-0.2.dist-info/top_level.txt
repo2jupyterlite-0.2.dist-info/RECORD
