Metadata-Version: 2.1
Name: repo2jupyterlite
Version: 0.2
Summary: Build JupyterLite bundles from code repositories
Home-page: https://github.com/yuvipanda/repo2jupyterlite/
Author: Yuvi Panda
Author-email: yuvipanda@gmail.com
License: 3-BSD
Project-URL: Source, https://github.com/yuvipanda/repo2jupyterlite/
Project-URL: Tracker, https://github.com/jupyterhub/repo2docker/issues
Classifier: Environment :: Console
Classifier: Intended Audience :: Developers
Classifier: Intended Audience :: System Administrators
Classifier: Intended Audience :: Science/Research
Classifier: License :: OSI Approved :: BSD License
Classifier: Programming Language :: Python
Classifier: Programming Language :: Python :: 3
Requires-Python: >=3.6
License-File: LICENSE
Requires-Dist: jupyterlite
Requires-Dist: jupyterlab
Requires-Dist: jupyterlite-xeus-python
Requires-Dist: jupyter-repo2docker
